Metadata-Version: 2.1
Name: ox3apiclient
Version: 0.6.1
Summary: Client to connect to the OpenX Enterprise API.
Home-page: https://github.com/openx/OX3-Python-API-Client
Author: OpenX API Team
Author-email: api@openx.com
License: BSD
Platform: POSIX
Classifier: Environment :: Console
Classifier: Environment :: Web Environment
Classifier: Intended Audience :: Developers
Classifier: Operating System :: OS Independent
Classifier: License :: OSI Approved :: BSD License
Classifier: Programming Language :: Python
Classifier: Programming Language :: Python :: 2.6
Classifier: Programming Language :: Python :: 2.7
Classifier: Programming Language :: Python :: 3
Classifier: Programming Language :: Python :: Implementation :: CPython
Classifier: Topic :: Internet :: WWW/HTTP :: Dynamic Content
Classifier: Topic :: Software Development :: Libraries
Classifier: Topic :: Software Development :: Libraries :: Python Modules
